{
  "project_info": {
    "project_number": "724102581775",
    "project_id": "newproject-1b9d2",
    "storage_bucket": "newproject-1b9d2.appspot.com"
  },
  "client": [
    {
      "client_info": {
        "mobilesdk_app_id": "1:724102581775:android:d1c3ec0aa2c34a66e21d7a",
        "android_client_info": {
          "package_name": "com.example.firebase"
        }
      },
      "oauth_client": [],
      "api_key": [
        {
          "current_key": "AIzaSyBnvWrUiHFZ15ndVVQAHz6VjNK4jpHG5Zg"
        }
      ],
      "services": {
        "appinvite_service": {
          "other_platform_oauth_client": []
        }
      }
    }
  ],
  "configuration_version": "1"
}